LICENSE
stupiddb2/__init__.py
stupiddb2/stupiddb.py
stupiddb2/stupidlock.py
stupiddb2-1.0.2.dist-info/LICENSE
stupiddb2-1.0.2.dist-info/METADATA
stupiddb2-1.0.2.dist-info/WHEEL
stupiddb2-1.0.2.dist-info/RECORD
