Metadata-Version: 2.1
Name: stupiddb2
Version: 1.0.2
Summary: an incredibly stupid, for fun, json "db"
Home-page: https://github.com/JaffarA/stupiddb
License: GPLv3
Author: Jaffar Almaleki
Author-email: jaffar.almaleki@gmail.com
Requires-Python: >=3.11,<4.0
Classifier: License :: Other/Proprietary License
Classifier: Programming Language :: Python :: 3
Classifier: Programming Language :: Python :: 3.11
Classifier: Programming Language :: Python :: 3.12
Project-URL: Repository, https://github.com/JaffarA/stupiddb
